tvpy/__init__.py
tvpy/addic7ed.py
tvpy/config.py
tvpy/console.py
tvpy/index.css
tvpy/index.html
tvpy/index.js
tvpy/lt.py
tvpy/main.py
tvpy/subs.py
tvpy/tmdb.py
tvpy/tv_clean.py
tvpy/tv_download.py
tvpy/tv_follow.py
tvpy/tv_html.py
tvpy/tv_info.py
tvpy/tv_rename.py
tvpy/tv_subs.py
tvpy/tv_tmdb.py
tvpy/tvpy.py
tvpy/util.py
tvpy/wizdom.py
tvpy-0.0.46.dist-info/METADATA
tvpy-0.0.46.dist-info/entry_points.txt
tvpy-0.0.46.dist-info/WHEEL
tvpy-0.0.46.dist-info/RECORD
