Metadata-Version: 2.1
Name: tvpy
Version: 0.0.46
Summary: 📺 TvPy
Home-page: https://github.com/gkutiel/tvpy/tree/master
Author: Gilad Kutiel
Author-email: gilad.kutiel@gmail.com
Requires-Python: >=3.10,<4.0
Classifier: Programming Language :: Python :: 3
Classifier: Programming Language :: Python :: 3.10
Classifier: Programming Language :: Python :: 3.11
Requires-Dist: 1337x (>=1.2.3,<2.0.0)
Requires-Dist: Pillow (>=9.2.0,<10.0.0)
Requires-Dist: cssselect (>=1.2.0,<2.0.0)
Requires-Dist: fire (>=0.4.0,<0.5.0)
Requires-Dist: humanize (>=4.4.0,<5.0.0)
Requires-Dist: libtorrent (>=2.0.7,<3.0.0)
Requires-Dist: lxml (>=4.9.1,<5.0.0)
Requires-Dist: parse-torrent-title (>=2.4,<3.0)
Requires-Dist: pyright (>=1.1.273,<2.0.0)
Requires-Dist: rich (>=12.5.1,<13.0.0)
Requires-Dist: simple-term-menu (>=1.5.2,<2.0.0)
Requires-Dist: toml (>=0.10.2,<0.11.0)
Requires-Dist: tqdm (>=4.64.0,<5.0.0)
Project-URL: Documentation, https://github.com/gkutiel/tvpy/tree/master
Project-URL: Repository, https://github.com/gkutiel/tvpy/tree/master
